es_cloud_secret_manager/__init__.py
es_cloud_secret_manager/aws_secret_manager.py
es_cloud_secret_manager/gcp_secret_manager.py
es_cloud_secret_manager/main.py
es_cloud_secret_manager/secret_manager.py
es_cloud_secret_manager-2.0.6.dist-info/LICENSE
es_cloud_secret_manager-2.0.6.dist-info/METADATA
es_cloud_secret_manager-2.0.6.dist-info/WHEEL
es_cloud_secret_manager-2.0.6.dist-info/entry_points.txt
es_cloud_secret_manager-2.0.6.dist-info/RECORD
