Metadata-Version: 2.1
Name: es-cloud-secret-manager
Version: 2.0.6
Summary: 
Author: nmarghetti
Author-email: marghettinicolas@hotmail.com
Requires-Python: >=3.13,<4.0
Classifier: Programming Language :: Python :: 3
Classifier: Programming Language :: Python :: 3.13
Requires-Dist: boto3 (>=1.36.6,<2.0.0)
Requires-Dist: google-cloud-secret-manager (>=2.22.1,<3.0.0)
Requires-Dist: google-crc32c (>=1.6.0,<2.0.0)
Requires-Dist: pyyaml (>=6.0.2,<7.0.0)
